flowtool_githooks_demo/__init__.py
flowtool_githooks_demo/_version.py
flowtool_githooks_demo/hooks.py
flowtool_githooks_demo-0.7.24.dist-info/DESCRIPTION.rst
flowtool_githooks_demo-0.7.24.dist-info/METADATA
flowtool_githooks_demo-0.7.24.dist-info/RECORD
flowtool_githooks_demo-0.7.24.dist-info/WHEEL
flowtool_githooks_demo-0.7.24.dist-info/entry_points.txt
flowtool_githooks_demo-0.7.24.dist-info/metadata.json
flowtool_githooks_demo-0.7.24.dist-info/top_level.txt
