Metadata-Version: 2.0
Name: flowtool-githooks-demo
Version: 0.7.24
Summary: Trivial demo tasks for git users.
Home-page: https://github.com/isnok/py-flowlib
Author: Konstantin Martini
Author-email: k@tuxcode.org
License: UNKNOWN
Keywords: git,flow,shell,local,example,demo,commandline
Platform: Debian/GNU Linux
Classifier: Development Status :: 3 - Alpha
Classifier: Programming Language :: Python
Classifier: Programming Language :: Python :: 2.7
Classifier: Programming Language :: Python :: 3.3
Classifier: Programming Language :: Python :: 3.4
Classifier: Programming Language :: Python :: 3.5
Classifier: Topic :: System :: Software Distribution
Classifier: Topic :: System :: Systems Administration
Classifier: Topic :: Utilities
Classifier: Intended Audience :: Developers
Classifier: Intended Audience :: System Administrators
Classifier: Operating System :: POSIX
Classifier: Operating System :: Unix
Classifier: Environment :: Console
Requires-Dist: flowtool-base (>=0.7.56)
Requires-Dist: flowtool-git (>=0.7.23)
Requires-Dist: flowtool-githooks (>=0.7.43)
Requires-Dist: pylint (>=1.5.5)
Requires-Dist: yamllint (>=1.2.1)
